{"nodes": [{"id": "c_users_mohammed_desktop_aslam_pop_campregistrationapp_project_nomination_prd_md", "label": "project_nomination_prd.md", "file_type": "document", "source_file": "CampRegistrationApp/project_nomination_prd.md", "source_location": "L1"}, {"id": "campregistrationapp_project_nomination_prd_prd_\u0646\u0638\u0627\u0645_\u0627\u0644\u062a\u0631\u0634\u064a\u062d\u0627\u062a_\u0644\u0644\u0645\u0634\u0627\u0631\u064a\u0639", "label": "PRD \u2013 \u0646\u0638\u0627\u0645 \u0627\u0644\u062a\u0631\u0634\u064a\u062d\u0627\u062a \u0644\u0644\u0645\u0634\u0627\u0631\u064a\u0639", "file_type": "document", "source_file": "CampRegistrationApp/project_nomination_prd.md", "source_location": "L1"}, {"id": "campregistrationapp_project_nomination_prd_\u0627\u0633\u0645_\u0627\u0644\u0645\u064a\u0632\u0629", "label": "\u0627\u0633\u0645 \u0627\u0644\u0645\u064a\u0632\u0629", "file_type": "document", "source_file": "CampRegistrationApp/project_nomination_prd.md", "source_location": "L3"}, {"id": "campregistrationapp_project_nomination_prd_1_\u0627\u0644\u0647\u062f\u0641_\u0645\u0646_\u0627\u0644\u0646\u0638\u0627\u0645", "label": "1. \u0627\u0644\u0647\u062f\u0641 \u0645\u0646 \u0627\u0644\u0646\u0638\u0627\u0645", "file_type": "document", "source_file": "CampRegistrationApp/project_nomination_prd.md", "source_location": "L8"}, {"id": "campregistrationapp_project_nomination_prd_2_\u0627\u0644\u0623\u0637\u0631\u0627\u0641_\u0627\u0644\u0645\u0633\u062a\u062e\u062f\u0645\u0629_\u0644\u0644\u0646\u0638\u0627\u0645", "label": "2. \u0627\u0644\u0623\u0637\u0631\u0627\u0641 \u0627\u0644\u0645\u0633\u062a\u062e\u062f\u0645\u0629 \u0644\u0644\u0646\u0638\u0627\u0645", "file_type": "document", "source_file": "CampRegistrationApp/project_nomination_prd.md", "source_location": "L14"}, {"id": "campregistrationapp_project_nomination_prd_3_\u0625\u0646\u0634\u0627\u0621_\u0645\u0634\u0631\u0648\u0639_\u062c\u062f\u064a\u062f_admin", "label": "3. \u0625\u0646\u0634\u0627\u0621 \u0645\u0634\u0631\u0648\u0639 \u062c\u062f\u064a\u062f (Admin)", "file_type": "document", "source_file": "CampRegistrationApp/project_nomination_prd.md", "source_location": "L24"}, {"id": "campregistrationapp_project_nomination_prd_\u0635\u0641\u062d\u0629_\u0625\u062f\u0627\u0631\u0629_\u0627\u0644\u0645\u0634\u0627\u0631\u064a\u0639", "label": "\u0635\u0641\u062d\u0629: \u0625\u062f\u0627\u0631\u0629 \u0627\u0644\u0645\u0634\u0627\u0631\u064a\u0639", "file_type": "document", "source_file": "CampRegistrationApp/project_nomination_prd.md", "source_location": "L26"}, {"id": "campregistrationapp_project_nomination_prd_\u0627\u0644\u062d\u0642\u0648\u0644_\u0627\u0644\u0645\u0637\u0644\u0648\u0628\u0629", "label": "\u0627\u0644\u062d\u0642\u0648\u0644 \u0627\u0644\u0645\u0637\u0644\u0648\u0628\u0629", "file_type": "document", "source_file": "CampRegistrationApp/project_nomination_prd.md", "source_location": "L30"}, {"id": "campregistrationapp_project_nomination_prd_4_\u0635\u0644\u0627\u062d\u064a\u0627\u062a_\u0627\u0644\u0645\u0634\u0631\u0648\u0639", "label": "4. \u0635\u0644\u0627\u062d\u064a\u0627\u062a \u0627\u0644\u0645\u0634\u0631\u0648\u0639", "file_type": "document", "source_file": "CampRegistrationApp/project_nomination_prd.md", "source_location": "L43"}, {"id": "campregistrationapp_project_nomination_prd_\u0627\u0644\u0645\u0646\u062f\u0648\u0628", "label": "\u0627\u0644\u0645\u0646\u062f\u0648\u0628", "file_type": "document", "source_file": "CampRegistrationApp/project_nomination_prd.md", "source_location": "L45"}, {"id": "campregistrationapp_project_nomination_prd_\u0627\u0644\u0623\u062f\u0645\u0646", "label": "\u0627\u0644\u0623\u062f\u0645\u0646", "file_type": "document", "source_file": "CampRegistrationApp/project_nomination_prd.md", "source_location": "L52"}, {"id": "campregistrationapp_project_nomination_prd_5_\u0635\u0641\u062d\u0629_\u0627\u0644\u062a\u0631\u0634\u064a\u062d\u0627\u062a_\u0644\u0644\u0645\u0646\u062f\u0648\u0628", "label": "5. \u0635\u0641\u062d\u0629 \u0627\u0644\u062a\u0631\u0634\u064a\u062d\u0627\u062a \u0644\u0644\u0645\u0646\u062f\u0648\u0628", "file_type": "document", "source_file": "CampRegistrationApp/project_nomination_prd.md", "source_location": "L61"}, {"id": "campregistrationapp_project_nomination_prd_\u0634\u0643\u0644_\u0627\u0644\u0635\u0641\u062d\u0629", "label": "\u0634\u0643\u0644 \u0627\u0644\u0635\u0641\u062d\u0629", "file_type": "document", "source_file": "CampRegistrationApp/project_nomination_prd.md", "source_location": "L63"}, {"id": "campregistrationapp_project_nomination_prd_\u0623\u0639\u0645\u062f\u0629_\u0627\u0644\u062c\u062f\u0648\u0644", "label": "\u0623\u0639\u0645\u062f\u0629 \u0627\u0644\u062c\u062f\u0648\u0644", "file_type": "document", "source_file": "CampRegistrationApp/project_nomination_prd.md", "source_location": "L73"}, {"id": "campregistrationapp_project_nomination_prd_6_\u0627\u0644\u0628\u062d\u062b_\u0639\u0646_\u0627\u0644\u0623\u0634\u062e\u0627\u0635", "label": "6. \u0627\u0644\u0628\u062d\u062b \u0639\u0646 \u0627\u0644\u0623\u0634\u062e\u0627\u0635", "file_type": "document", "source_file": "CampRegistrationApp/project_nomination_prd.md", "source_location": "L89"}, {"id": "campregistrationapp_project_nomination_prd_\u0627\u0644\u0645\u0645\u064a\u0632\u0627\u062a", "label": "\u0627\u0644\u0645\u0645\u064a\u0632\u0627\u062a", "file_type": "document", "source_file": "CampRegistrationApp/project_nomination_prd.md", "source_location": "L93"}, {"id": "campregistrationapp_project_nomination_prd_7_\u0645\u0646\u0639_\u0627\u0644\u062a\u0643\u0631\u0627\u0631_\u0648\u0627\u0644\u062a\u0646\u0628\u064a\u0647\u0627\u062a", "label": "7. \u0645\u0646\u0639 \u0627\u0644\u062a\u0643\u0631\u0627\u0631 \u0648\u0627\u0644\u062a\u0646\u0628\u064a\u0647\u0627\u062a", "file_type": "document", "source_file": "CampRegistrationApp/project_nomination_prd.md", "source_location": "L104"}, {"id": "campregistrationapp_project_nomination_prd_\u0627\u0644\u0633\u064a\u0646\u0627\u0631\u064a\u0648", "label": "\u0627\u0644\u0633\u064a\u0646\u0627\u0631\u064a\u0648", "file_type": "document", "source_file": "CampRegistrationApp/project_nomination_prd.md", "source_location": "L106"}, {"id": "campregistrationapp_project_nomination_prd_warning_message", "label": "Warning Message", "file_type": "document", "source_file": "CampRegistrationApp/project_nomination_prd.md", "source_location": "L115"}, {"id": "campregistrationapp_project_nomination_prd_\u0627\u0644\u0633\u0644\u0648\u0643", "label": "\u0627\u0644\u0633\u0644\u0648\u0643", "file_type": "document", "source_file": "CampRegistrationApp/project_nomination_prd.md", "source_location": "L119"}, {"id": "campregistrationapp_project_nomination_prd_8_\u0642\u0648\u0627\u0639\u062f_\u0627\u0644\u0639\u0645\u0644_business_rules", "label": "8. \u0642\u0648\u0627\u0639\u062f \u0627\u0644\u0639\u0645\u0644 (Business Rules)", "file_type": "document", "source_file": "CampRegistrationApp/project_nomination_prd.md", "source_location": "L127"}, {"id": "campregistrationapp_project_nomination_prd_\u0642\u0648\u0627\u0639\u062f_\u0627\u0644\u062a\u0631\u0634\u064a\u062d", "label": "\u0642\u0648\u0627\u0639\u062f \u0627\u0644\u062a\u0631\u0634\u064a\u062d", "file_type": "document", "source_file": "CampRegistrationApp/project_nomination_prd.md", "source_location": "L129"}, {"id": "campregistrationapp_project_nomination_prd_\u064a\u0645\u0646\u0639", "label": "\u064a\u0645\u0646\u0639:", "file_type": "document", "source_file": "CampRegistrationApp/project_nomination_prd.md", "source_location": "L131"}, {"id": "campregistrationapp_project_nomination_prd_\u064a\u0633\u0645\u062d", "label": "\u064a\u0633\u0645\u062d:", "file_type": "document", "source_file": "CampRegistrationApp/project_nomination_prd.md", "source_location": "L137"}, {"id": "campregistrationapp_project_nomination_prd_9_\u0627\u0644\u0627\u0639\u062a\u0645\u0627\u062f_\u0627\u0644\u0646\u0647\u0627\u0626\u064a", "label": "9. \u0627\u0644\u0627\u0639\u062a\u0645\u0627\u062f \u0627\u0644\u0646\u0647\u0627\u0626\u064a", "file_type": "document", "source_file": "CampRegistrationApp/project_nomination_prd.md", "source_location": "L145"}, {"id": "campregistrationapp_project_nomination_prd_\u062d\u0627\u0644\u0627\u062a_\u0627\u0644\u062a\u0631\u0634\u064a\u062d", "label": "\u062d\u0627\u0644\u0627\u062a \u0627\u0644\u062a\u0631\u0634\u064a\u062d", "file_type": "document", "source_file": "CampRegistrationApp/project_nomination_prd.md", "source_location": "L147"}, {"id": "campregistrationapp_project_nomination_prd_10_\u0627\u0644\u0640_auditing_\u0627\u0644\u0645\u0637\u0644\u0648\u0628", "label": "10. \u0627\u0644\u0640 Auditing \u0627\u0644\u0645\u0637\u0644\u0648\u0628", "file_type": "document", "source_file": "CampRegistrationApp/project_nomination_prd.md", "source_location": "L159"}, {"id": "campregistrationapp_project_nomination_prd_11_\u062a\u0641\u0627\u0635\u064a\u0644_\u0627\u0644\u0640_audit_log", "label": "11. \u062a\u0641\u0627\u0635\u064a\u0644 \u0627\u0644\u0640 Audit Log", "file_type": "document", "source_file": "CampRegistrationApp/project_nomination_prd.md", "source_location": "L177"}, {"id": "campregistrationapp_project_nomination_prd_\u0627\u0644\u0628\u064a\u0627\u0646\u0627\u062a_\u0627\u0644\u0645\u0637\u0644\u0648\u0628\u0629", "label": "\u0627\u0644\u0628\u064a\u0627\u0646\u0627\u062a \u0627\u0644\u0645\u0637\u0644\u0648\u0628\u0629", "file_type": "document", "source_file": "CampRegistrationApp/project_nomination_prd.md", "source_location": "L179"}, {"id": "campregistrationapp_project_nomination_prd_12_\u0642\u0627\u0639\u062f\u0629_\u0627\u0644\u0628\u064a\u0627\u0646\u0627\u062a_\u0627\u0644\u0645\u0642\u062a\u0631\u062d\u0629", "label": "12. \u0642\u0627\u0639\u062f\u0629 \u0627\u0644\u0628\u064a\u0627\u0646\u0627\u062a \u0627\u0644\u0645\u0642\u062a\u0631\u062d\u0629", "file_type": "document", "source_file": "CampRegistrationApp/project_nomination_prd.md", "source_location": "L194"}, {"id": "campregistrationapp_project_nomination_prd_\u0627\u0644\u062c\u062f\u0627\u0648\u0644_\u0627\u0644\u0631\u0626\u064a\u0633\u064a\u0629", "label": "\u0627\u0644\u062c\u062f\u0627\u0648\u0644 \u0627\u0644\u0631\u0626\u064a\u0633\u064a\u0629", "file_type": "document", "source_file": "CampRegistrationApp/project_nomination_prd.md", "source_location": "L196"}, {"id": "campregistrationapp_project_nomination_prd_projects", "label": "Projects", "file_type": "document", "source_file": "CampRegistrationApp/project_nomination_prd.md", "source_location": "L198"}, {"id": "campregistrationapp_project_nomination_prd_projectnominations", "label": "ProjectNominations", "file_type": "document", "source_file": "CampRegistrationApp/project_nomination_prd.md", "source_location": "L213"}, {"id": "campregistrationapp_project_nomination_prd_auditlogs", "label": "AuditLogs", "file_type": "document", "source_file": "CampRegistrationApp/project_nomination_prd.md", "source_location": "L233"}, {"id": "campregistrationapp_project_nomination_prd_13_\u0627\u0644\u0640_api_\u0627\u0644\u0645\u0637\u0644\u0648\u0628\u0629", "label": "13. \u0627\u0644\u0640 API \u0627\u0644\u0645\u0637\u0644\u0648\u0628\u0629", "file_type": "document", "source_file": "CampRegistrationApp/project_nomination_prd.md", "source_location": "L248"}, {"id": "campregistrationapp_project_nomination_prd_projects_apis", "label": "Projects APIs", "file_type": "document", "source_file": "CampRegistrationApp/project_nomination_prd.md", "source_location": "L250"}, {"id": "campregistrationapp_project_nomination_prd_nominations_apis", "label": "Nominations APIs", "file_type": "document", "source_file": "CampRegistrationApp/project_nomination_prd.md", "source_location": "L260"}, {"id": "campregistrationapp_project_nomination_prd_14_\u0627\u0644\u0645\u062a\u0637\u0644\u0628\u0627\u062a_\u0627\u0644\u062a\u0642\u0646\u064a\u0629", "label": "14. \u0627\u0644\u0645\u062a\u0637\u0644\u0628\u0627\u062a \u0627\u0644\u062a\u0642\u0646\u064a\u0629", "file_type": "document", "source_file": "CampRegistrationApp/project_nomination_prd.md", "source_location": "L272"}, {"id": "campregistrationapp_project_nomination_prd_frontend", "label": "Frontend", "file_type": "document", "source_file": "CampRegistrationApp/project_nomination_prd.md", "source_location": "L274"}, {"id": "campregistrationapp_project_nomination_prd_backend", "label": "Backend", "file_type": "document", "source_file": "CampRegistrationApp/project_nomination_prd.md", "source_location": "L284"}, {"id": "campregistrationapp_project_nomination_prd_15_\u0627\u0644\u062a\u0642\u0627\u0631\u064a\u0631_\u0627\u0644\u0645\u0637\u0644\u0648\u0628\u0629", "label": "15. \u0627\u0644\u062a\u0642\u0627\u0631\u064a\u0631 \u0627\u0644\u0645\u0637\u0644\u0648\u0628\u0629", "file_type": "document", "source_file": "CampRegistrationApp/project_nomination_prd.md", "source_location": "L294"}, {"id": "campregistrationapp_project_nomination_prd_\u062a\u0642\u0627\u0631\u064a\u0631_\u0627\u0644\u0623\u062f\u0645\u0646", "label": "\u062a\u0642\u0627\u0631\u064a\u0631 \u0627\u0644\u0623\u062f\u0645\u0646", "file_type": "document", "source_file": "CampRegistrationApp/project_nomination_prd.md", "source_location": "L296"}, {"id": "campregistrationapp_project_nomination_prd_16_\u062a\u062d\u0633\u064a\u0646\u0627\u062a_\u0645\u0633\u062a\u0642\u0628\u0644\u064a\u0629", "label": "16. \u062a\u062d\u0633\u064a\u0646\u0627\u062a \u0645\u0633\u062a\u0642\u0628\u0644\u064a\u0629", "file_type": "document", "source_file": "CampRegistrationApp/project_nomination_prd.md", "source_location": "L306"}, {"id": "campregistrationapp_project_nomination_prd_17_\u0645\u0644\u0627\u062d\u0638\u0627\u062a_\u0645\u0647\u0645\u0629_\u0644\u0644\u062a\u0646\u0641\u064a\u0630", "label": "17. \u0645\u0644\u0627\u062d\u0638\u0627\u062a \u0645\u0647\u0645\u0629 \u0644\u0644\u062a\u0646\u0641\u064a\u0630", "file_type": "document", "source_file": "CampRegistrationApp/project_nomination_prd.md", "source_location": "L316"}], "edges": [{"source": "c_users_mohammed_desktop_aslam_pop_campregistrationapp_project_nomination_prd_md", "target": "campregistrationapp_project_nomination_prd_prd_\u0646\u0638\u0627\u0645_\u0627\u0644\u062a\u0631\u0634\u064a\u062d\u0627\u062a_\u0644\u0644\u0645\u0634\u0627\u0631\u064a\u0639", "relation": "contains", "confidence": "EXTRACTED", "source_file": "CampRegistrationApp/project_nomination_prd.md", "source_location": "L1", "weight": 1.0}, {"source": "campregistrationapp_project_nomination_prd_prd_\u0646\u0638\u0627\u0645_\u0627\u0644\u062a\u0631\u0634\u064a\u062d\u0627\u062a_\u0644\u0644\u0645\u0634\u0627\u0631\u064a\u0639", "target": "campregistrationapp_project_nomination_prd_\u0627\u0633\u0645_\u0627\u0644\u0645\u064a\u0632\u0629", "relation": "contains", "confidence": "EXTRACTED", "source_file": "CampRegistrationApp/project_nomination_prd.md", "source_location": "L3", "weight": 1.0}, {"source": "c_users_mohammed_desktop_aslam_pop_campregistrationapp_project_nomination_prd_md", "target": "campregistrationapp_project_nomination_prd_1_\u0627\u0644\u0647\u062f\u0641_\u0645\u0646_\u0627\u0644\u0646\u0638\u0627\u0645", "relation": "contains", "confidence": "EXTRACTED", "source_file": "CampRegistrationApp/project_nomination_prd.md", "source_location": "L8", "weight": 1.0}, {"source": "c_users_mohammed_desktop_aslam_pop_campregistrationapp_project_nomination_prd_md", "target": "campregistrationapp_project_nomination_prd_2_\u0627\u0644\u0623\u0637\u0631\u0627\u0641_\u0627\u0644\u0645\u0633\u062a\u062e\u062f\u0645\u0629_\u0644\u0644\u0646\u0638\u0627\u0645", "relation": "contains", "confidence": "EXTRACTED", "source_file": "CampRegistrationApp/project_nomination_prd.md", "source_location": "L14", "weight": 1.0}, {"source": "c_users_mohammed_desktop_aslam_pop_campregistrationapp_project_nomination_prd_md", "target": "campregistrationapp_project_nomination_prd_3_\u0625\u0646\u0634\u0627\u0621_\u0645\u0634\u0631\u0648\u0639_\u062c\u062f\u064a\u062f_admin", "relation": "contains", "confidence": "EXTRACTED", "source_file": "CampRegistrationApp/project_nomination_prd.md", "source_location": "L24", "weight": 1.0}, {"source": "campregistrationapp_project_nomination_prd_3_\u0625\u0646\u0634\u0627\u0621_\u0645\u0634\u0631\u0648\u0639_\u062c\u062f\u064a\u062f_admin", "target": "campregistrationapp_project_nomination_prd_\u0635\u0641\u062d\u0629_\u0625\u062f\u0627\u0631\u0629_\u0627\u0644\u0645\u0634\u0627\u0631\u064a\u0639", "relation": "contains", "confidence": "EXTRACTED", "source_file": "CampRegistrationApp/project_nomination_prd.md", "source_location": "L26", "weight": 1.0}, {"source": "campregistrationapp_project_nomination_prd_\u0635\u0641\u062d\u0629_\u0625\u062f\u0627\u0631\u0629_\u0627\u0644\u0645\u0634\u0627\u0631\u064a\u0639", "target": "campregistrationapp_project_nomination_prd_\u0627\u0644\u062d\u0642\u0648\u0644_\u0627\u0644\u0645\u0637\u0644\u0648\u0628\u0629", "relation": "contains", "confidence": "EXTRACTED", "source_file": "CampRegistrationApp/project_nomination_prd.md", "source_location": "L30", "weight": 1.0}, {"source": "c_users_mohammed_desktop_aslam_pop_campregistrationapp_project_nomination_prd_md", "target": "campregistrationapp_project_nomination_prd_4_\u0635\u0644\u0627\u062d\u064a\u0627\u062a_\u0627\u0644\u0645\u0634\u0631\u0648\u0639", "relation": "contains", "confidence": "EXTRACTED", "source_file": "CampRegistrationApp/project_nomination_prd.md", "source_location": "L43", "weight": 1.0}, {"source": "campregistrationapp_project_nomination_prd_4_\u0635\u0644\u0627\u062d\u064a\u0627\u062a_\u0627\u0644\u0645\u0634\u0631\u0648\u0639", "target": "campregistrationapp_project_nomination_prd_\u0627\u0644\u0645\u0646\u062f\u0648\u0628", "relation": "contains", "confidence": "EXTRACTED", "source_file": "CampRegistrationApp/project_nomination_prd.md", "source_location": "L45", "weight": 1.0}, {"source": "campregistrationapp_project_nomination_prd_4_\u0635\u0644\u0627\u062d\u064a\u0627\u062a_\u0627\u0644\u0645\u0634\u0631\u0648\u0639", "target": "campregistrationapp_project_nomination_prd_\u0627\u0644\u0623\u062f\u0645\u0646", "relation": "contains", "confidence": "EXTRACTED", "source_file": "CampRegistrationApp/project_nomination_prd.md", "source_location": "L52", "weight": 1.0}, {"source": "c_users_mohammed_desktop_aslam_pop_campregistrationapp_project_nomination_prd_md", "target": "campregistrationapp_project_nomination_prd_5_\u0635\u0641\u062d\u0629_\u0627\u0644\u062a\u0631\u0634\u064a\u062d\u0627\u062a_\u0644\u0644\u0645\u0646\u062f\u0648\u0628", "relation": "contains", "confidence": "EXTRACTED", "source_file": "CampRegistrationApp/project_nomination_prd.md", "source_location": "L61", "weight": 1.0}, {"source": "campregistrationapp_project_nomination_prd_5_\u0635\u0641\u062d\u0629_\u0627\u0644\u062a\u0631\u0634\u064a\u062d\u0627\u062a_\u0644\u0644\u0645\u0646\u062f\u0648\u0628", "target": "campregistrationapp_project_nomination_prd_\u0634\u0643\u0644_\u0627\u0644\u0635\u0641\u062d\u0629", "relation": "contains", "confidence": "EXTRACTED", "source_file": "CampRegistrationApp/project_nomination_prd.md", "source_location": "L63", "weight": 1.0}, {"source": "campregistrationapp_project_nomination_prd_5_\u0635\u0641\u062d\u0629_\u0627\u0644\u062a\u0631\u0634\u064a\u062d\u0627\u062a_\u0644\u0644\u0645\u0646\u062f\u0648\u0628", "target": "campregistrationapp_project_nomination_prd_\u0623\u0639\u0645\u062f\u0629_\u0627\u0644\u062c\u062f\u0648\u0644", "relation": "contains", "confidence": "EXTRACTED", "source_file": "CampRegistrationApp/project_nomination_prd.md", "source_location": "L73", "weight": 1.0}, {"source": "c_users_mohammed_desktop_aslam_pop_campregistrationapp_project_nomination_prd_md", "target": "campregistrationapp_project_nomination_prd_6_\u0627\u0644\u0628\u062d\u062b_\u0639\u0646_\u0627\u0644\u0623\u0634\u062e\u0627\u0635", "relation": "contains", "confidence": "EXTRACTED", "source_file": "CampRegistrationApp/project_nomination_prd.md", "source_location": "L89", "weight": 1.0}, {"source": "campregistrationapp_project_nomination_prd_6_\u0627\u0644\u0628\u062d\u062b_\u0639\u0646_\u0627\u0644\u0623\u0634\u062e\u0627\u0635", "target": "campregistrationapp_project_nomination_prd_\u0627\u0644\u0645\u0645\u064a\u0632\u0627\u062a", "relation": "contains", "confidence": "EXTRACTED", "source_file": "CampRegistrationApp/project_nomination_prd.md", "source_location": "L93", "weight": 1.0}, {"source": "c_users_mohammed_desktop_aslam_pop_campregistrationapp_project_nomination_prd_md", "target": "campregistrationapp_project_nomination_prd_7_\u0645\u0646\u0639_\u0627\u0644\u062a\u0643\u0631\u0627\u0631_\u0648\u0627\u0644\u062a\u0646\u0628\u064a\u0647\u0627\u062a", "relation": "contains", "confidence": "EXTRACTED", "source_file": "CampRegistrationApp/project_nomination_prd.md", "source_location": "L104", "weight": 1.0}, {"source": "campregistrationapp_project_nomination_prd_7_\u0645\u0646\u0639_\u0627\u0644\u062a\u0643\u0631\u0627\u0631_\u0648\u0627\u0644\u062a\u0646\u0628\u064a\u0647\u0627\u062a", "target": "campregistrationapp_project_nomination_prd_\u0627\u0644\u0633\u064a\u0646\u0627\u0631\u064a\u0648", "relation": "contains", "confidence": "EXTRACTED", "source_file": "CampRegistrationApp/project_nomination_prd.md", "source_location": "L106", "weight": 1.0}, {"source": "campregistrationapp_project_nomination_prd_\u0627\u0644\u0633\u064a\u0646\u0627\u0631\u064a\u0648", "target": "campregistrationapp_project_nomination_prd_warning_message", "relation": "contains", "confidence": "EXTRACTED", "source_file": "CampRegistrationApp/project_nomination_prd.md", "source_location": "L115", "weight": 1.0}, {"source": "campregistrationapp_project_nomination_prd_\u0627\u0644\u0633\u064a\u0646\u0627\u0631\u064a\u0648", "target": "campregistrationapp_project_nomination_prd_\u0627\u0644\u0633\u0644\u0648\u0643", "relation": "contains", "confidence": "EXTRACTED", "source_file": "CampRegistrationApp/project_nomination_prd.md", "source_location": "L119", "weight": 1.0}, {"source": "c_users_mohammed_desktop_aslam_pop_campregistrationapp_project_nomination_prd_md", "target": "campregistrationapp_project_nomination_prd_8_\u0642\u0648\u0627\u0639\u062f_\u0627\u0644\u0639\u0645\u0644_business_rules", "relation": "contains", "confidence": "EXTRACTED", "source_file": "CampRegistrationApp/project_nomination_prd.md", "source_location": "L127", "weight": 1.0}, {"source": "campregistrationapp_project_nomination_prd_8_\u0642\u0648\u0627\u0639\u062f_\u0627\u0644\u0639\u0645\u0644_business_rules", "target": "campregistrationapp_project_nomination_prd_\u0642\u0648\u0627\u0639\u062f_\u0627\u0644\u062a\u0631\u0634\u064a\u062d", "relation": "contains", "confidence": "EXTRACTED", "source_file": "CampRegistrationApp/project_nomination_prd.md", "source_location": "L129", "weight": 1.0}, {"source": "campregistrationapp_project_nomination_prd_\u0642\u0648\u0627\u0639\u062f_\u0627\u0644\u062a\u0631\u0634\u064a\u062d", "target": "campregistrationapp_project_nomination_prd_\u064a\u0645\u0646\u0639", "relation": "contains", "confidence": "EXTRACTED", "source_file": "CampRegistrationApp/project_nomination_prd.md", "source_location": "L131", "weight": 1.0}, {"source": "campregistrationapp_project_nomination_prd_\u0642\u0648\u0627\u0639\u062f_\u0627\u0644\u062a\u0631\u0634\u064a\u062d", "target": "campregistrationapp_project_nomination_prd_\u064a\u0633\u0645\u062d", "relation": "contains", "confidence": "EXTRACTED", "source_file": "CampRegistrationApp/project_nomination_prd.md", "source_location": "L137", "weight": 1.0}, {"source": "c_users_mohammed_desktop_aslam_pop_campregistrationapp_project_nomination_prd_md", "target": "campregistrationapp_project_nomination_prd_9_\u0627\u0644\u0627\u0639\u062a\u0645\u0627\u062f_\u0627\u0644\u0646\u0647\u0627\u0626\u064a", "relation": "contains", "confidence": "EXTRACTED", "source_file": "CampRegistrationApp/project_nomination_prd.md", "source_location": "L145", "weight": 1.0}, {"source": "campregistrationapp_project_nomination_prd_9_\u0627\u0644\u0627\u0639\u062a\u0645\u0627\u062f_\u0627\u0644\u0646\u0647\u0627\u0626\u064a", "target": "campregistrationapp_project_nomination_prd_\u062d\u0627\u0644\u0627\u062a_\u0627\u0644\u062a\u0631\u0634\u064a\u062d", "relation": "contains", "confidence": "EXTRACTED", "source_file": "CampRegistrationApp/project_nomination_prd.md", "source_location": "L147", "weight": 1.0}, {"source": "c_users_mohammed_desktop_aslam_pop_campregistrationapp_project_nomination_prd_md", "target": "campregistrationapp_project_nomination_prd_10_\u0627\u0644\u0640_auditing_\u0627\u0644\u0645\u0637\u0644\u0648\u0628", "relation": "contains", "confidence": "EXTRACTED", "source_file": "CampRegistrationApp/project_nomination_prd.md", "source_location": "L159", "weight": 1.0}, {"source": "c_users_mohammed_desktop_aslam_pop_campregistrationapp_project_nomination_prd_md", "target": "campregistrationapp_project_nomination_prd_11_\u062a\u0641\u0627\u0635\u064a\u0644_\u0627\u0644\u0640_audit_log", "relation": "contains", "confidence": "EXTRACTED", "source_file": "CampRegistrationApp/project_nomination_prd.md", "source_location": "L177", "weight": 1.0}, {"source": "campregistrationapp_project_nomination_prd_11_\u062a\u0641\u0627\u0635\u064a\u0644_\u0627\u0644\u0640_audit_log", "target": "campregistrationapp_project_nomination_prd_\u0627\u0644\u0628\u064a\u0627\u0646\u0627\u062a_\u0627\u0644\u0645\u0637\u0644\u0648\u0628\u0629", "relation": "contains", "confidence": "EXTRACTED", "source_file": "CampRegistrationApp/project_nomination_prd.md", "source_location": "L179", "weight": 1.0}, {"source": "c_users_mohammed_desktop_aslam_pop_campregistrationapp_project_nomination_prd_md", "target": "campregistrationapp_project_nomination_prd_12_\u0642\u0627\u0639\u062f\u0629_\u0627\u0644\u0628\u064a\u0627\u0646\u0627\u062a_\u0627\u0644\u0645\u0642\u062a\u0631\u062d\u0629", "relation": "contains", "confidence": "EXTRACTED", "source_file": "CampRegistrationApp/project_nomination_prd.md", "source_location": "L194", "weight": 1.0}, {"source": "campregistrationapp_project_nomination_prd_12_\u0642\u0627\u0639\u062f\u0629_\u0627\u0644\u0628\u064a\u0627\u0646\u0627\u062a_\u0627\u0644\u0645\u0642\u062a\u0631\u062d\u0629", "target": "campregistrationapp_project_nomination_prd_\u0627\u0644\u062c\u062f\u0627\u0648\u0644_\u0627\u0644\u0631\u0626\u064a\u0633\u064a\u0629", "relation": "contains", "confidence": "EXTRACTED", "source_file": "CampRegistrationApp/project_nomination_prd.md", "source_location": "L196", "weight": 1.0}, {"source": "campregistrationapp_project_nomination_prd_\u0627\u0644\u062c\u062f\u0627\u0648\u0644_\u0627\u0644\u0631\u0626\u064a\u0633\u064a\u0629", "target": "campregistrationapp_project_nomination_prd_projects", "relation": "contains", "confidence": "EXTRACTED", "source_file": "CampRegistrationApp/project_nomination_prd.md", "source_location": "L198", "weight": 1.0}, {"source": "campregistrationapp_project_nomination_prd_\u0627\u0644\u062c\u062f\u0627\u0648\u0644_\u0627\u0644\u0631\u0626\u064a\u0633\u064a\u0629", "target": "campregistrationapp_project_nomination_prd_projectnominations", "relation": "contains", "confidence": "EXTRACTED", "source_file": "CampRegistrationApp/project_nomination_prd.md", "source_location": "L213", "weight": 1.0}, {"source": "campregistrationapp_project_nomination_prd_\u0627\u0644\u062c\u062f\u0627\u0648\u0644_\u0627\u0644\u0631\u0626\u064a\u0633\u064a\u0629", "target": "campregistrationapp_project_nomination_prd_auditlogs", "relation": "contains", "confidence": "EXTRACTED", "source_file": "CampRegistrationApp/project_nomination_prd.md", "source_location": "L233", "weight": 1.0}, {"source": "c_users_mohammed_desktop_aslam_pop_campregistrationapp_project_nomination_prd_md", "target": "campregistrationapp_project_nomination_prd_13_\u0627\u0644\u0640_api_\u0627\u0644\u0645\u0637\u0644\u0648\u0628\u0629", "relation": "contains", "confidence": "EXTRACTED", "source_file": "CampRegistrationApp/project_nomination_prd.md", "source_location": "L248", "weight": 1.0}, {"source": "campregistrationapp_project_nomination_prd_13_\u0627\u0644\u0640_api_\u0627\u0644\u0645\u0637\u0644\u0648\u0628\u0629", "target": "campregistrationapp_project_nomination_prd_projects_apis", "relation": "contains", "confidence": "EXTRACTED", "source_file": "CampRegistrationApp/project_nomination_prd.md", "source_location": "L250", "weight": 1.0}, {"source": "campregistrationapp_project_nomination_prd_13_\u0627\u0644\u0640_api_\u0627\u0644\u0645\u0637\u0644\u0648\u0628\u0629", "target": "campregistrationapp_project_nomination_prd_nominations_apis", "relation": "contains", "confidence": "EXTRACTED", "source_file": "CampRegistrationApp/project_nomination_prd.md", "source_location": "L260", "weight": 1.0}, {"source": "c_users_mohammed_desktop_aslam_pop_campregistrationapp_project_nomination_prd_md", "target": "campregistrationapp_project_nomination_prd_14_\u0627\u0644\u0645\u062a\u0637\u0644\u0628\u0627\u062a_\u0627\u0644\u062a\u0642\u0646\u064a\u0629", "relation": "contains", "confidence": "EXTRACTED", "source_file": "CampRegistrationApp/project_nomination_prd.md", "source_location": "L272", "weight": 1.0}, {"source": "campregistrationapp_project_nomination_prd_14_\u0627\u0644\u0645\u062a\u0637\u0644\u0628\u0627\u062a_\u0627\u0644\u062a\u0642\u0646\u064a\u0629", "target": "campregistrationapp_project_nomination_prd_frontend", "relation": "contains", "confidence": "EXTRACTED", "source_file": "CampRegistrationApp/project_nomination_prd.md", "source_location": "L274", "weight": 1.0}, {"source": "campregistrationapp_project_nomination_prd_14_\u0627\u0644\u0645\u062a\u0637\u0644\u0628\u0627\u062a_\u0627\u0644\u062a\u0642\u0646\u064a\u0629", "target": "campregistrationapp_project_nomination_prd_backend", "relation": "contains", "confidence": "EXTRACTED", "source_file": "CampRegistrationApp/project_nomination_prd.md", "source_location": "L284", "weight": 1.0}, {"source": "c_users_mohammed_desktop_aslam_pop_campregistrationapp_project_nomination_prd_md", "target": "campregistrationapp_project_nomination_prd_15_\u0627\u0644\u062a\u0642\u0627\u0631\u064a\u0631_\u0627\u0644\u0645\u0637\u0644\u0648\u0628\u0629", "relation": "contains", "confidence": "EXTRACTED", "source_file": "CampRegistrationApp/project_nomination_prd.md", "source_location": "L294", "weight": 1.0}, {"source": "campregistrationapp_project_nomination_prd_15_\u0627\u0644\u062a\u0642\u0627\u0631\u064a\u0631_\u0627\u0644\u0645\u0637\u0644\u0648\u0628\u0629", "target": "campregistrationapp_project_nomination_prd_\u062a\u0642\u0627\u0631\u064a\u0631_\u0627\u0644\u0623\u062f\u0645\u0646", "relation": "contains", "confidence": "EXTRACTED", "source_file": "CampRegistrationApp/project_nomination_prd.md", "source_location": "L296", "weight": 1.0}, {"source": "c_users_mohammed_desktop_aslam_pop_campregistrationapp_project_nomination_prd_md", "target": "campregistrationapp_project_nomination_prd_16_\u062a\u062d\u0633\u064a\u0646\u0627\u062a_\u0645\u0633\u062a\u0642\u0628\u0644\u064a\u0629", "relation": "contains", "confidence": "EXTRACTED", "source_file": "CampRegistrationApp/project_nomination_prd.md", "source_location": "L306", "weight": 1.0}, {"source": "c_users_mohammed_desktop_aslam_pop_campregistrationapp_project_nomination_prd_md", "target": "campregistrationapp_project_nomination_prd_17_\u0645\u0644\u0627\u062d\u0638\u0627\u062a_\u0645\u0647\u0645\u0629_\u0644\u0644\u062a\u0646\u0641\u064a\u0630", "relation": "contains", "confidence": "EXTRACTED", "source_file": "CampRegistrationApp/project_nomination_prd.md", "source_location": "L316", "weight": 1.0}], "input_tokens": 0, "output_tokens": 0}